{
  "params": {
    "color": {"type": "color", "default": "#1565C0"},
    "label": {"type": "string", "default": ""}
  },
  "width": 60,
  "height": 55,
  "elements": [
    {"type": "circle", "x": 30, "y": 20, "r": 18, "style": {"fill": "#E3F2FD", "stroke": "{{color}}", "strokeWidth": 2}},
    {"type": "path", "d": "M 22 14 L 30 8 L 38 14", "style": {"fill": "none", "stroke": "{{color}}", "strokeWidth": 2.5, "strokeLinecap": "round", "strokeLinejoin": "round"}},
    {"type": "line", "x": 30, "y": 8, "x2": 30, "y2": 20, "style": {"stroke": "{{color}}", "strokeWidth": 2.5}},
    {"type": "line", "x": 22, "y": 20, "x2": 38, "y2": 20, "style": {"stroke": "{{color}}", "strokeWidth": 2}},
    {"type": "path", "d": "M 22 20 L 18 28", "style": {"stroke": "{{color}}", "strokeWidth": 2.5, "strokeLinecap": "round"}},
    {"type": "path", "d": "M 30 20 L 30 28", "style": {"stroke": "{{color}}", "strokeWidth": 2.5, "strokeLinecap": "round"}},
    {"type": "path", "d": "M 38 20 L 42 28", "style": {"stroke": "{{color}}", "strokeWidth": 2.5, "strokeLinecap": "round"}},
    {"type": "circle", "x": 18, "y": 30, "r": 3, "style": {"fill": "{{color}}"}},
    {"type": "circle", "x": 30, "y": 30, "r": 3, "style": {"fill": "{{color}}"}},
    {"type": "circle", "x": 42, "y": 30, "r": 3, "style": {"fill": "{{color}}"}},
    {"type": "text", "x": 30, "y": 50, "text": "{{label}}", "align": "center", "style": {"fontSize": 9, "fill": "#333"}, "if": "label"}
  ]
}
